Metadata-Version: 2.1
Name: phone-number-generator
Version: 0.1.1
Summary: All countries phone number generator.
Home-page: https://github.com/mosesoyediran/number-generator.git
Author: Moses D
Author-email: mosesoyedran01@gmail.com
License: MIT
Keywords: All countries phone number generator
Classifier: License :: OSI Approved :: MIT License
Classifier: Programming Language :: Python :: 3.12
License-File: LICENSE.txt
